fconcrete/__init__.py
fconcrete/cli.py
fconcrete/config.py
fconcrete/fconcrete.py
fconcrete/helpers.py
fconcrete/Structural/Beam.py
fconcrete/Structural/BeamElement.py
fconcrete/Structural/Load.py
fconcrete/Structural/Material.py
fconcrete/Structural/Node.py
fconcrete/Structural/Section.py
fconcrete/Structural/__init__.py
fconcrete/StructuralConcrete/Analysis.py
fconcrete/StructuralConcrete/AvailableMaterials.py
fconcrete/StructuralConcrete/Concrete.py
fconcrete/StructuralConcrete/ConcreteBeam.py
fconcrete/StructuralConcrete/__init__.py
fconcrete/StructuralConcrete/LongSteelBar/LongSteelBar.py
fconcrete/StructuralConcrete/LongSteelBar/LongSteelBarSolve.py
fconcrete/StructuralConcrete/LongSteelBar/__init__.py
fconcrete/StructuralConcrete/TransvSteelBar/TransvSteelBar.py
fconcrete/StructuralConcrete/TransvSteelBar/TransvSteelBarSolve.py
fconcrete/StructuralConcrete/TransvSteelBar/__init__.py
fconcrete-0.1.0.dist-info/AUTHORS.rst
fconcrete-0.1.0.dist-info/LICENSE
fconcrete-0.1.0.dist-info/METADATA
fconcrete-0.1.0.dist-info/WHEEL
fconcrete-0.1.0.dist-info/entry_points.txt
fconcrete-0.1.0.dist-info/top_level.txt
fconcrete-0.1.0.dist-info/RECORD
