Metadata-Version: 2.1
Name: fconcrete
Version: 0.1.0
Summary: Concrete beams according to NBR:6118:2014
Home-page: https://github.com/luisggc/fconcrete
Author: Luis Gabriel Gonçalves Coimbra
Author-email: luiscoimbraeng@outlook.com
License: MIT license
Keywords: fconcrete
Platform: UNKNOWN
Classifier: Development Status :: 2 - Pre-Alpha
Classifier: Intended Audience :: Developers
Classifier: License :: OSI Approved :: MIT License
Classifier: Natural Language :: English
Classifier: Programming Language :: Python :: 3
Classifier: Programming Language :: Python :: 3.5
Classifier: Programming Language :: Python :: 3.6
Classifier: Programming Language :: Python :: 3.7
Classifier: Programming Language :: Python :: 3.8
Requires-Python: >=3.5
Requires-Dist: Click (>=7.0)
